octotui/__init__.py
octotui/__main__.py
octotui/commit_graph.py
octotui/custom_figlet_widget.py
octotui/diff_markdown.py
octotui/gac_config_modal.py
octotui/gac_integration.py
octotui/gac_provider_registry.py
octotui/git_diff_viewer.py
octotui/git_status_sidebar.py
octotui/graph_actions.py
octotui/graph_data.py
octotui/graph_layout.py
octotui/main.py
octotui/octotui_logo.py
octotui/style.tcss
octotui/syntax_utils.py
octotui-0.1.8.data/data/octotui/style.tcss
octotui-0.1.8.dist-info/METADATA
octotui-0.1.8.dist-info/WHEEL
octotui-0.1.8.dist-info/entry_points.txt
octotui-0.1.8.dist-info/RECORD
