Metadata-Version: 2.4
Name: octotui
Version: 0.1.8
Summary: A blazing-fast TUI replacement for GitKraken - manage your Git repos with style!
Project-URL: Repository, https://github.com/never-use-gui/octotui
Project-URL: Homepage, https://github.com/never-use-gui/octotui
Project-URL: Bug Tracker, https://github.com/never-use-gui/octotui/issues
Author-email: Michael Pfaffenberger <michael@pfaffenberger.dev>
License: MIT
Keywords: git,gitkraken,terminal,textual,tui,version-control
Classifier: Environment :: Console
Classifier: Intended Audience :: Developers
Classifier: License :: OSI Approved :: MIT License
Classifier: Operating System :: OS Independent
Classifier: Programming Language :: Python :: 3
Classifier: Programming Language :: Python :: 3.11
Classifier: Programming Language :: Python :: 3.12
Classifier: Programming Language :: Python :: 3.13
Classifier: Topic :: Software Development :: Version Control :: Git
Classifier: Topic :: Terminals
Requires-Python: >=3.11
Requires-Dist: gac>=2.7.3
Requires-Dist: gitpython>=3.1.42
Requires-Dist: pyfiglet>=1.0.2
Requires-Dist: textual>=6.1.0
